dvwap/__init__.py
dvwap/data_formater.py
dvwap/deep_static_vwap.py
dvwap/dynamic_standard_vwap.py
dvwap/losses.py
dvwap-0.1.0.dist-info/METADATA
dvwap-0.1.0.dist-info/WHEEL
dvwap-0.1.0.dist-info/RECORD
