Metadata-Version: 2.1
Name: dvwap
Version: 0.1.0
Summary: Deep-Learning for Optimal VWAP Execution
Author: Rémi Genet
Requires-Python: >=3.9,<3.13
Classifier: Programming Language :: Python :: 3
Classifier: Programming Language :: Python :: 3.9
Classifier: Programming Language :: Python :: 3.10
Classifier: Programming Language :: Python :: 3.11
Classifier: Programming Language :: Python :: 3.12
Requires-Dist: keras (>=3.0.0,<4.0.0)
Requires-Dist: scikit-learn (>=1.5.2,<2.0.0)
Requires-Dist: temporal_linear_network (>=0.1.2,<0.2.0)
